clickhouse_manager/__init__.py
clickhouse_manager/clickhouse_manager.py
clickhouse_manager/validators.py
clickhouse_manager/connectors/__init__.py
clickhouse_manager/connectors/base_connector.py
clickhouse_manager/connectors/clickhouse_connect_connector.py
clickhouse_manager/connectors/clickhouse_driver_connector.py
clickhouse_manager/connectors/factory.py
clickhouse_manager-0.1.3.dist-info/licenses/LICENSE
clickhouse_manager-0.1.3.dist-info/METADATA
clickhouse_manager-0.1.3.dist-info/WHEEL
clickhouse_manager-0.1.3.dist-info/top_level.txt
clickhouse_manager-0.1.3.dist-info/RECORD
